mammos_ai/__init__.py
mammos_ai/py.typed
mammos_ai/_beyond_stoner_wohlfarth_fixed_angle/__init__.py
mammos_ai/_beyond_stoner_wohlfarth_fixed_angle/classifier_cube50_singlegrain_random_forest_v0.1.onnx
mammos_ai/_beyond_stoner_wohlfarth_fixed_angle/hard_cube50_singlegrain_random_forest_v0.1.onnx
mammos_ai/_beyond_stoner_wohlfarth_fixed_angle/soft_cube50_singlegrain_random_forest_v0.1.onnx
mammos_ai-0.2.0.dist-info/METADATA
mammos_ai-0.2.0.dist-info/WHEEL
mammos_ai-0.2.0.dist-info/licenses/LICENSE
mammos_ai-0.2.0.dist-info/RECORD
