Metadata-Version: 2.4
Name: mammos-ai
Version: 0.2.0
Summary: Pre-trained AI models
Project-URL: Homepage, https://MaMMoS-project.github.io
Project-URL: Documentation, https://mammos-project.github.io/mammos
Project-URL: Repository, https://github.com/MaMMoS-project/mammos-ai
Project-URL: Issues, https://github.com/MaMMoS-project/mammos-ai/issues
Project-URL: Changelog, https://mammos-project.github.io/mammos/changelog
Author: Christina Winkler, Timoteo Colnaghi, Swapneel Amit Pathak, Andrea Petrocchi, Samuel Holt, Martin Lang, Hans Fangohr, Andreas Marek
License-Expression: MIT
License-File: LICENSE
Classifier: Intended Audience :: Developers
Classifier: Intended Audience :: Education
Classifier: Intended Audience :: Science/Research
Classifier: Programming Language :: Python :: 3 :: Only
Classifier: Topic :: Scientific/Engineering :: Physics
Requires-Python: >=3.11
Requires-Dist: mammos-analysis
Requires-Dist: mammos-entity
Requires-Dist: mammos-units
Requires-Dist: onnxruntime
